Metadata-Version: 2.1
Name: despatchbay
Version: 1.0.0
Summary: Python SDK for the Despatch Bay API v15
Home-page: https://github.com/despatchbay/despatchbay-python-sdk
Author: Scott Keenan
Author-email: scott.keenan@thesalegroup.co.uk
License: UNKNOWN
Download-URL: https://github.com/despatchbay/despatchbay-python-sdk/archive/v1.0.0.tar.gz
Platform: UNKNOWN
Classifier: Programming Language :: Python :: 3
Classifier: License :: OSI Approved :: MIT License
Classifier: Operating System :: OS Independent
